retackAI_sdk/__init__.py
retackAI_sdk/retack_client.py
retackAI_sdk_django-1.0.2.dist-info/LICENSE
retackAI_sdk_django-1.0.2.dist-info/METADATA
retackAI_sdk_django-1.0.2.dist-info/WHEEL
retackAI_sdk_django-1.0.2.dist-info/top_level.txt
retackAI_sdk_django-1.0.2.dist-info/RECORD
