Metadata-Version: 2.1
Name: retackAI-sdk-django
Version: 1.0.2
Summary: Retack SDK for Django
Home-page: https://github.com/truenary/retack_pkg_python
Author: Truenary
Author-email: contact@truenary.com
License: MIT
License-File: LICENSE
Requires-Dist: requests
